map4/__init__.py
map4/map4.py
map4_ojmb-1.0.dist-info/LICENSE.md
map4_ojmb-1.0.dist-info/METADATA
map4_ojmb-1.0.dist-info/WHEEL
map4_ojmb-1.0.dist-info/top_level.txt
map4_ojmb-1.0.dist-info/RECORD
