Metadata-Version: 2.1
Name: map4-ojmb
Version: 1.0
Summary: MinHashed AtomPair Fingerprint of Radius 2
Home-page: https://github.com/OlivierBeq/map4
Author: Alice Capecchi
Author-email: alice.capecchi@outlook.it
Maintainer: Olivier J. M. Béquignon
Maintainer-email: olivier.bequignon.maintainer@gmail.com
License-File: LICENSE.md
Requires-Dist: faerun
Requires-Dist: mhfp
Requires-Dist: rdkit
